py_semantic_taxonomy/__init__.py
py_semantic_taxonomy/app.py
py_semantic_taxonomy/cfg.py
py_semantic_taxonomy/dependencies.py
py_semantic_taxonomy/adapters/persistence/__init__.py
py_semantic_taxonomy/adapters/persistence/database.py
py_semantic_taxonomy/adapters/persistence/graph.py
py_semantic_taxonomy/adapters/persistence/search_engine.py
py_semantic_taxonomy/adapters/persistence/tables.py
py_semantic_taxonomy/adapters/persistence/sql/broader_concept_hierarchy.sql
py_semantic_taxonomy/adapters/routers/__init__.py
py_semantic_taxonomy/adapters/routers/api_router.py
py_semantic_taxonomy/adapters/routers/catch_router.py
py_semantic_taxonomy/adapters/routers/doc_examples.py
py_semantic_taxonomy/adapters/routers/request_dto.py
py_semantic_taxonomy/adapters/routers/response_dto.py
py_semantic_taxonomy/adapters/routers/validation.py
py_semantic_taxonomy/adapters/routers/web_router.py
py_semantic_taxonomy/adapters/routers/static/css/pyst.css
py_semantic_taxonomy/adapters/routers/static/img/logo.png
py_semantic_taxonomy/adapters/routers/templates/base.html
py_semantic_taxonomy/adapters/routers/templates/concept_scheme_view.html
py_semantic_taxonomy/adapters/routers/templates/concept_schemes.html
py_semantic_taxonomy/adapters/routers/templates/concept_view.html
py_semantic_taxonomy/adapters/routers/templates/search.html
py_semantic_taxonomy/application/__init__.py
py_semantic_taxonomy/application/graph_service.py
py_semantic_taxonomy/application/search_service.py
py_semantic_taxonomy/domain/__init__.py
py_semantic_taxonomy/domain/constants.py
py_semantic_taxonomy/domain/entities.py
py_semantic_taxonomy/domain/hash_utils.py
py_semantic_taxonomy/domain/ports.py
py_semantic_taxonomy/domain/url_utils.py
py_semantic_taxonomy-0.4.4.dist-info/licenses/LICENSE
py_semantic_taxonomy-0.4.4.dist-info/METADATA
py_semantic_taxonomy-0.4.4.dist-info/WHEEL
py_semantic_taxonomy-0.4.4.dist-info/top_level.txt
py_semantic_taxonomy-0.4.4.dist-info/RECORD
