Metadata-Version: 2.4
Name: py_semantic_taxonomy
Version: 0.4.4
Summary: Python webapp and API for SKOS semantic taxonomies
Author-email: Chris Mutel <chris@cauldron.ch>
Maintainer-email: Chris Mutel <chris@cauldron.ch>
Project-URL: source, https://github.com/cauldron/py-semantic-taxonomy
Project-URL: homepage, https://github.com/cauldron/py-semantic-taxonomy
Project-URL: tracker, https://github.com/cauldron/py-semantic-taxonomy/issues
Classifier: Development Status :: 4 - Beta
Classifier: Programming Language :: Python
Classifier: Programming Language :: Python :: 3
Classifier: Programming Language :: Python :: 3.12
Classifier: Programming Language :: Python :: 3.13
Classifier: Natural Language :: English
Classifier: Operating System :: OS Independent
Classifier: Topic :: Scientific/Engineering
Requires-Python: >=3.12
License-File: LICENSE
Requires-Dist: asyncpg
Requires-Dist: fastapi
Requires-Dist: fastapi_pagination
Requires-Dist: jinja2
Requires-Dist: langcodes
Requires-Dist: language-data
Requires-Dist: orjson
Requires-Dist: pydantic>=2
Requires-Dist: pydantic_settings
Requires-Dist: rdflib
Requires-Dist: rfc3987
Requires-Dist: sqlalchemy>=2.0
Requires-Dist: structlog
Requires-Dist: pyst_typesense_async
Requires-Dist: uvicorn
Provides-Extra: testing
Requires-Dist: aiosqlite; extra == "testing"
Requires-Dist: faker; extra == "testing"
Requires-Dist: httpx; extra == "testing"
Requires-Dist: py_semantic_taxonomy; extra == "testing"
Requires-Dist: pytest; extra == "testing"
Requires-Dist: pytest-asyncio; extra == "testing"
Requires-Dist: pytest-cov; extra == "testing"
Requires-Dist: pytest-randomly; extra == "testing"
Requires-Dist: pytest-antilru; extra == "testing"
Requires-Dist: python-coveralls; extra == "testing"
Requires-Dist: testcontainers[postgres]; extra == "testing"
Provides-Extra: dev
Requires-Dist: build; extra == "dev"
Requires-Dist: pre-commit; extra == "dev"
Requires-Dist: aiosqlite; extra == "dev"
Requires-Dist: httpx; extra == "dev"
Requires-Dist: mkdocs; extra == "dev"
Requires-Dist: mkdocs-material; extra == "dev"
Requires-Dist: pylint; extra == "dev"
Requires-Dist: pytest; extra == "dev"
Requires-Dist: pytest-antilru; extra == "dev"
Requires-Dist: pytest-asyncio; extra == "dev"
Requires-Dist: pytest-cov; extra == "dev"
Requires-Dist: pytest-randomly; extra == "dev"
Requires-Dist: setuptools; extra == "dev"
Requires-Dist: testcontainers[postgres]; extra == "dev"
Dynamic: license-file
